{"content":"明天中午吃什么？","ip":"::1","time":"2017-09-08T03:18:51.632Z","username":"guo123","answers":[{"content":"什么也行！！","time":"2017-09-08T07:02:08.088Z","ip":"::1","username":"guo123"},{"content":"什么也行！！","time":"2017-09-08T07:05:25.465Z","ip":"::1","username":"guo123"},{"content":"什么也行！！","time":"2017-09-08T07:05:31.554Z","ip":"::1","username":"guo123"},{"content":"sasas","time":"2017-09-22T12:50:17.710Z","ip":"::1","username":"123123"},{"content":"sasasas","time":"2017-09-22T12:50:26.228Z","ip":"::1","username":"123123"},{"content":"sasasa","time":"2017-09-22T12:50:39.798Z","ip":"::1","username":"123123"},{"content":"sasasa","time":"2017-09-22T12:50:47.725Z","ip":"::1","username":"123123"}]}